[
    {
        "X": -14.5,
        "Y": -6.900000095367432,
        "airRes": false,
        "coefficentOfFriction": 0.5,
        "color": 4294967295,
        "gravity": false,
        "height": 10.0,
        "layer": 0,
        "loc": "blank.png",
        "mass": 10.0,
        "objectType": -2,
        "pointList": [
            0.0,
            0.0,
            0.0,
            0.0,
            0.0,
            0.0,
            0.0,
            0.0,
            0.0,
            0.0,
            0.0,
            0.0,
            0.0,
            0.0,
            0.0,
            0.0,
            0.0,
            0.0,
            0.0,
            0.0,
            0.0,
            0.0,
            0.0,
            0.0,
            0.0,
            0.0,
            0.0,
            0.0,
            0.0,
            0.0
        ],
        "points": 0,
        "rotation": 0.0,
        "sides": 0,
        "sizeModifier": 0.0,
        "solid": false,
        "text": "lorium ipsum",
        "trigger": {
            "destroyO2": false,
            "event": "none",
            "id": "default",
            "typeReq": 1
        },
        "txtLbl": "default",
        "velRot": 0.0,
        "velX": 0.0,
        "velY": 0.0,
        "width": 20.0
    },
    {
        "X": -48.0,
        "Y": -28.0,
        "airRes": true,
        "coefficentOfFriction": 0.5,
        "color": 4294967295,
        "gravity": false,
        "height": 10.0,
        "layer": 0,
        "loc": "blank.png",
        "mass": 10.0,
        "objectType": -1,
        "pointList": [
            0.0,
            0.0,
            0.0,
            0.0,
            0.0,
            0.0,
            0.0,
            0.0,
            0.0,
            0.0,
            0.0,
            0.0,
            0.0,
            0.0,
            0.0,
            0.0,
            0.0,
            0.0,
            0.0,
            0.0,
            0.0,
            0.0,
            0.0,
            0.0,
            0.0,
            0.0,
            0.0,
            0.0,
            0.0,
            0.0
        ],
        "points": 0,
        "rotation": 0.0,
        "sides": 0,
        "sizeModifier": 0.0,
        "solid": true,
        "text": "lorium ipsum",
        "trigger": {
            "destroyO2": false,
            "event": "none",
            "id": "default",
            "typeReq": 1
        },
        "txtLbl": "default",
        "velRot": 0.0,
        "velX": 0.0,
        "velY": 0.0,
        "width": 20.0
    },
    {
        "X": 8.07067584991455,
        "Y": 23.35023307800293,
        "airRes": true,
        "coefficentOfFriction": 0.5,
        "color": 707670783,
        "gravity": false,
        "height": 10.0,
        "layer": 0,
        "loc": "blank.png",
        "mass": -1.0,
        "objectType": 2,
        "pointList": [
            -0.0,
            1.0,
            0.0,
            0.0,
            0.0,
            0.0,
            1.0,
            0.0,
            511.6226806640625,
            407.5843200683594,
            0.0,
            1.0,
            1.0,
            0.0,
            0.0,
            0.0,
            0.0,
            1.0,
            0.0,
            0.0,
            0.0,
            0.0,
            1.0,
            0.0,
            0.0,
            0.0,
            0.0,
            1.0,
            3.587324068671532e-43,
            0.0
        ],
        "points": 0,
        "rotation": 0.0,
        "sides": 3,
        "sizeModifier": 2.0,
        "solid": true,
        "text": "lorium ipsum",
        "trigger": {
            "destroyO2": false,
            "event": "none",
            "id": "default",
            "typeReq": 1
        },
        "txtLbl": "default",
        "velRot": 0.0,
        "velX": 0.0,
        "velY": 0.0,
        "width": 20.0
    },
    {
        "X": -11.500004768371582,
        "Y": 4.500002384185791,
        "airRes": true,
        "coefficentOfFriction": 0.5,
        "color": 4278255615,
        "gravity": true,
        "height": 10.0,
        "layer": 0,
        "loc": "blank.png",
        "mass": 10.0,
        "objectType": 3,
        "pointList": [
            -0.0,
            1.0,
            0.0,
            0.0,
            0.0,
            0.0,
            1.0,
            0.0,
            546.936279296875,
            350.00006103515625,
            0.0,
            1.0,
            1.0,
            0.0,
            0.0,
            0.0,
            0.0,
            1.0,
            0.0,
            0.0,
            0.0,
            0.0,
            1.0,
            0.0,
            0.0,
            0.0,
            0.0,
            1.0,
            3.587324068671532e-43,
            0.0
        ],
        "points": 0,
        "rotation": 190.0,
        "sides": 4,
        "sizeModifier": 2.0,
        "solid": true,
        "text": "lorium ipsum",
        "trigger": {
            "destroyO2": false,
            "event": "none",
            "id": "default",
            "typeReq": 1
        },
        "txtLbl": "default",
        "velRot": 0.0,
        "velX": 0.0,
        "velY": 0.0,
        "width": 20.0
    },
    {
        "X": -110.3293228149414,
        "Y": 23.250219345092773,
        "airRes": true,
        "coefficentOfFriction": 0.5,
        "color": 707670783,
        "gravity": false,
        "height": 10.0,
        "layer": 0,
        "loc": "blank.png",
        "mass": -1.0,
        "objectType": 2,
        "pointList": [
            -0.0,
            1.0,
            0.0,
            0.0,
            0.0,
            0.0,
            1.0,
            0.0,
            408.59844970703125,
            187.9264678955078,
            0.0,
            1.0,
            1.0,
            0.0,
            0.0,
            0.0,
            0.0,
            1.0,
            0.0,
            0.0,
            0.0,
            0.0,
            1.0,
            0.0,
            0.0,
            0.0,
            0.0,
            1.0,
            3.587324068671532e-43,
            0.0
        ],
        "points": 0,
        "rotation": -180.0,
        "sides": 3,
        "sizeModifier": 2.0,
        "solid": true,
        "text": "lorium ipsum",
        "trigger": {
            "destroyO2": false,
            "event": "none",
            "id": "default",
            "typeReq": 1
        },
        "txtLbl": "default",
        "velRot": 0.0,
        "velX": 0.0,
        "velY": 0.0,
        "width": 20.0
    },
    {
        "X": -90.83930969238281,
        "Y": 23.470230102539063,
        "airRes": true,
        "coefficentOfFriction": 0.5,
        "color": 707670783,
        "gravity": false,
        "height": 10.0,
        "layer": 0,
        "loc": "blank.png",
        "mass": -1.0,
        "objectType": 2,
        "pointList": [
            -0.0,
            1.0,
            0.0,
            0.0,
            0.0,
            0.0,
            1.0,
            0.0,
            187.8802490234375,
            630.76123046875,
            0.0,
            1.0,
            1.0,
            0.0,
            0.0,
            0.0,
            0.0,
            1.0,
            0.0,
            0.0,
            0.0,
            0.0,
            1.0,
            0.0,
            0.0,
            0.0,
            0.0,
            1.0,
            3.587324068671532e-43,
            0.0
        ],
        "points": 0,
        "rotation": -180.0,
        "sides": 3,
        "sizeModifier": 2.0,
        "solid": true,
        "text": "lorium ipsum",
        "trigger": {
            "destroyO2": false,
            "event": "none",
            "id": "default",
            "typeReq": 1
        },
        "txtLbl": "default",
        "velRot": 0.0,
        "velX": 0.0,
        "velY": 0.0,
        "width": 20.0
    },
    {
        "X": -51.62932205200195,
        "Y": 23.450231552124023,
        "airRes": true,
        "coefficentOfFriction": 0.5,
        "color": 707670783,
        "gravity": false,
        "height": 10.0,
        "layer": 0,
        "loc": "blank.png",
        "mass": -1.0,
        "objectType": 2,
        "pointList": [
            -0.0,
            1.0,
            0.0,
            0.0,
            0.0,
            0.0,
            1.0,
            0.0,
            410.9363098144531,
            440.00006103515625,
            0.0,
            1.0,
            1.0,
            0.0,
            0.0,
            0.0,
            0.0,
            1.0,
            0.0,
            0.0,
            0.0,
            0.0,
            1.0,
            0.0,
            0.0,
            0.0,
            0.0,
            1.0,
            3.587324068671532e-43,
            0.0
        ],
        "points": 0,
        "rotation": -180.0,
        "sides": 3,
        "sizeModifier": 2.0,
        "solid": true,
        "text": "lorium ipsum",
        "trigger": {
            "destroyO2": false,
            "event": "none",
            "id": "default",
            "typeReq": 1
        },
        "txtLbl": "default",
        "velRot": 0.0,
        "velX": 0.0,
        "velY": 0.0,
        "width": 20.0
    },
    {
        "X": -71.30457305908203,
        "Y": 23.432058334350586,
        "airRes": true,
        "coefficentOfFriction": 0.5,
        "color": 707670783,
        "gravity": false,
        "height": 10.0,
        "layer": 0,
        "loc": "blank.png",
        "mass": -1.0,
        "objectType": 2,
        "pointList": [
            -0.0,
            1.0,
            0.0,
            0.0,
            0.0,
            0.0,
            1.0,
            0.0,
            799.936279296875,
            490.00006103515625,
            0.0,
            1.0,
            1.0,
            0.0,
            0.0,
            0.0,
            0.0,
            1.0,
            0.0,
            0.0,
            0.0,
            0.0,
            1.0,
            0.0,
            0.0,
            0.0,
            0.0,
            1.0,
            3.587324068671532e-43,
            0.0
        ],
        "points": 0,
        "rotation": -180.0,
        "sides": 3,
        "sizeModifier": 2.0,
        "solid": true,
        "text": "lorium ipsum",
        "trigger": {
            "destroyO2": false,
            "event": "none",
            "id": "default",
            "typeReq": 1
        },
        "txtLbl": "default",
        "velRot": 0.0,
        "velX": 0.0,
        "velY": 0.0,
        "width": 20.0
    },
    {
        "X": -11.929313659667969,
        "Y": 23.450231552124023,
        "airRes": true,
        "coefficentOfFriction": 0.5,
        "color": 707670783,
        "gravity": false,
        "height": 10.0,
        "layer": 0,
        "loc": "blank.png",
        "mass": -1.0,
        "objectType": 2,
        "pointList": [
            -0.0,
            1.0,
            0.0,
            0.0,
            0.0,
            0.0,
            1.0,
            0.0,
            586.936279296875,
            500.00006103515625,
            0.0,
            1.0,
            1.0,
            0.0,
            0.0,
            0.0,
            0.0,
            1.0,
            0.0,
            0.0,
            0.0,
            0.0,
            1.0,
            0.0,
            0.0,
            0.0,
            0.0,
            1.0,
            3.587324068671532e-43,
            0.0
        ],
        "points": 0,
        "rotation": -180.0,
        "sides": 3,
        "sizeModifier": 2.0,
        "solid": true,
        "text": "lorium ipsum",
        "trigger": {
            "destroyO2": false,
            "event": "none",
            "id": "default",
            "typeReq": 1
        },
        "txtLbl": "default",
        "velRot": 0.0,
        "velX": 0.0,
        "velY": 0.0,
        "width": 20.0
    },
    {
        "X": -31.72931671142578,
        "Y": 23.450231552124023,
        "airRes": true,
        "coefficentOfFriction": 0.5,
        "color": 707670783,
        "gravity": false,
        "height": 10.0,
        "layer": 0,
        "loc": "blank.png",
        "mass": -1.0,
        "objectType": 2,
        "pointList": [
            -0.0,
            1.0,
            0.0,
            0.0,
            0.0,
            0.0,
            1.0,
            0.0,
            655.936279296875,
            248.00006103515625,
            0.0,
            1.0,
            1.0,
            0.0,
            0.0,
            0.0,
            0.0,
            1.0,
            0.0,
            0.0,
            0.0,
            0.0,
            1.0,
            0.0,
            0.0,
            0.0,
            0.0,
            1.0,
            3.587324068671532e-43,
            0.0
        ],
        "points": 0,
        "rotation": -180.0,
        "sides": 3,
        "sizeModifier": 2.0,
        "solid": true,
        "text": "lorium ipsum",
        "trigger": {
            "destroyO2": false,
            "event": "none",
            "id": "default",
            "typeReq": 1
        },
        "txtLbl": "default",
        "velRot": 0.0,
        "velX": 0.0,
        "velY": 0.0,
        "width": 20.0
    },
    {
        "X": -39.443870544433594,
        "Y": 16.60301399230957,
        "airRes": true,
        "coefficentOfFriction": 0.5,
        "color": 707670783,
        "gravity": false,
        "height": 10.0,
        "layer": 0,
        "loc": "blank.png",
        "mass": -1.0,
        "objectType": 0,
        "pointList": [
            1.8942855596542358,
            4.548571586608887,
            2.6942856311798096,
            0.2485712170600891,
            2.1942856311798096,
            -1.3714287281036377,
            -0.5857136845588684,
            -3.4514284133911133,
            -1.6557143926620483,
            -2.4514284133911133,
            -2.52571439743042,
            0.26857125759124756,
            -2.015714406967163,
            2.208571434020996,
            0.0,
            0.0,
            0.0,
            1.0,
            0.0,
            0.0,
            0.0,
            0.0,
            1.0,
            0.0,
            0.0,
            0.0,
            0.0,
            1.0,
            3.587324068671532e-43,
            13951.8984375
        ],
        "points": 7,
        "rotation": -198.0,
        "sides": 3,
        "sizeModifier": 2.0,
        "solid": true,
        "text": "lorium ipsum",
        "trigger": {
            "destroyO2": false,
            "event": "none",
            "id": "default",
            "typeReq": 1
        },
        "txtLbl": "default",
        "velRot": 0.0,
        "velX": 0.0,
        "velY": 0.0,
        "width": 20.0
    },
    {
        "X": 16.000003814697266,
        "Y": -3.8999977111816406,
        "airRes": true,
        "coefficentOfFriction": 0.5,
        "color": 4278255615,
        "gravity": true,
        "height": 10.0,
        "layer": 0,
        "loc": "blank.png",
        "mass": 10.0,
        "objectType": 1,
        "pointList": [
            -0.8660253882408142,
            -0.5000000596046448,
            0.0,
            0.0,
            0.0,
            0.0,
            1.0,
            0.0,
            455.6409912109375,
            602.3590087890625,
            0.0,
            1.0,
            1.0,
            0.0,
            0.0,
            0.0,
            0.0,
            1.0,
            0.0,
            0.0,
            0.0,
            0.0,
            1.0,
            0.0,
            0.0,
            0.0,
            0.0,
            1.0,
            3.587324068671532e-43,
            35215275720704.0
        ],
        "points": 0,
        "rotation": -495.0,
        "sides": 4,
        "sizeModifier": 2.030393600463867,
        "solid": true,
        "text": "lorium ipsum",
        "trigger": {
            "destroyO2": false,
            "event": "none",
            "id": "default",
            "typeReq": 1
        },
        "txtLbl": "default",
        "velRot": 0.0,
        "velX": 0.0,
        "velY": 0.0,
        "width": 20.0
    },
    {
        "X": -21.098831176757813,
        "Y": -9.088088989257813,
        "airRes": true,
        "coefficentOfFriction": 0.5,
        "color": 4294967295,
        "gravity": false,
        "height": 10.0,
        "layer": 0,
        "loc": "blank.png",
        "mass": -1.0,
        "objectType": 0,
        "pointList": [
            1.8942855596542358,
            4.548571586608887,
            2.6942856311798096,
            0.2485712170600891,
            2.1942856311798096,
            -1.3714287281036377,
            -0.5857136249542236,
            -3.4514284133911133,
            -1.6557143926620483,
            -2.4514284133911133,
            -2.52571439743042,
            0.26857125759124756,
            -2.015714406967163,
            2.208571434020996,
            0.0,
            0.0,
            0.0,
            1.0,
            0.0,
            0.0,
            0.0,
            0.0,
            1.0,
            0.0,
            0.0,
            0.0,
            0.0,
            1.0,
            3.587324068671532e-43,
            35217020551168.0
        ],
        "points": 7,
        "rotation": -270.0,
        "sides": 3,
        "sizeModifier": 2.0,
        "solid": true,
        "text": "lorium ipsum",
        "trigger": {
            "destroyO2": false,
            "event": "none",
            "id": "default",
            "typeReq": 1
        },
        "txtLbl": "default",
        "velRot": 0.0,
        "velX": 0.0,
        "velY": 0.0,
        "width": 20.0
    },
    {
        "X": -37.18018341064453,
        "Y": 6.779398441314697,
        "airRes": true,
        "coefficentOfFriction": 0.5,
        "color": 707670783,
        "gravity": false,
        "height": 10.0,
        "layer": 0,
        "loc": "blank.png",
        "mass": -1.0,
        "objectType": 0,
        "pointList": [
            -1.0,
            -4.371138828673793e-08,
            0.0,
            0.0,
            0.0,
            0.0,
            1.0,
            0.0,
            1134.0,
            461.0,
            0.0,
            1.0,
            1.0,
            0.0,
            0.0,
            0.0,
            0.0,
            1.0,
            0.0,
            0.0,
            0.0,
            0.0,
            1.0,
            0.0,
            0.0,
            0.0,
            0.0,
            1.0,
            3.587324068671532e-43,
            35218765381632.0
        ],
        "points": 0,
        "rotation": -378.0,
        "sides": 3,
        "sizeModifier": 2.0,
        "solid": true,
        "text": "lorium ipsum",
        "trigger": {
            "destroyO2": false,
            "event": "none",
            "id": "default",
            "typeReq": 1
        },
        "txtLbl": "default",
        "velRot": 0.0,
        "velX": 0.0,
        "velY": 0.0,
        "width": 20.0
    },
    {
        "X": -43.5,
        "Y": 11.700005531311035,
        "airRes": true,
        "coefficentOfFriction": 0.5,
        "color": 707670783,
        "gravity": false,
        "height": 0.0,
        "layer": 0,
        "loc": "blank.png",
        "mass": -1.0,
        "objectType": 0,
        "pointList": [
            -0.0,
            1.0,
            0.0,
            0.0,
            0.0,
            0.0,
            1.0,
            0.0,
            437.0,
            576.0,
            0.0,
            1.0,
            1.0,
            0.0,
            0.0,
            0.0,
            0.0,
            1.0,
            0.0,
            0.0,
            0.0,
            0.0,
            1.0,
            0.0,
            0.0,
            0.0,
            0.0,
            1.0,
            3.587324068671532e-43,
            35220510212096.0
        ],
        "points": 0,
        "rotation": -300.0,
        "sides": 3,
        "sizeModifier": 2.0,
        "solid": true,
        "text": "lorium ipsum",
        "trigger": {
            "destroyO2": false,
            "event": "none",
            "id": "default",
            "typeReq": 1
        },
        "txtLbl": "default",
        "velRot": 0.0,
        "velX": 0.0,
        "velY": 0.0,
        "width": 0.0
    },
    {
        "X": -33.24140167236328,
        "Y": 11.583161354064941,
        "airRes": true,
        "coefficentOfFriction": 0.5,
        "color": 707670783,
        "gravity": false,
        "height": 0.0,
        "layer": 0,
        "loc": "blank.png",
        "mass": -1.0,
        "objectType": 0,
        "pointList": [
            -0.866025447845459,
            0.4999999701976776,
            0.0,
            0.0,
            0.0,
            0.0,
            1.0,
            0.0,
            452.6410217285156,
            541.3590087890625,
            0.0,
            1.0,
            1.0,
            0.0,
            0.0,
            0.0,
            0.0,
            1.0,
            0.0,
            0.0,
            0.0,
            0.0,
            1.0,
            0.0,
            0.0,
            0.0,
            0.0,
            1.0,
            3.587324068671532e-43,
            35222255042560.0
        ],
        "points": 0,
        "rotation": -360.0,
        "sides": 3,
        "sizeModifier": 2.0416855812072754,
        "solid": true,
        "text": "lorium ipsum",
        "trigger": {
            "destroyO2": false,
            "event": "none",
            "id": "default",
            "typeReq": 1
        },
        "txtLbl": "default",
        "velRot": 0.0,
        "velX": 0.0,
        "velY": 0.0,
        "width": 0.0
    },
    {
        "X": -19.092060089111328,
        "Y": -5.704880714416504,
        "airRes": true,
        "coefficentOfFriction": 0.5,
        "color": 4294967295,
        "gravity": true,
        "height": 0.0,
        "layer": 0,
        "loc": "blank.png",
        "mass": 10.0,
        "objectType": 0,
        "pointList": [
            -0.0,
            1.0,
            0.0,
            0.0,
            0.0,
            0.0,
            1.0,
            0.0,
            231.71249389648438,
            284.1369934082031,
            0.0,
            1.0,
            1.0,
            0.0,
            0.0,
            0.0,
            0.0,
            1.0,
            0.0,
            0.0,
            0.0,
            0.0,
            1.0,
            0.0,
            0.0,
            0.0,
            0.0,
            1.0,
            3.587324068671532e-43,
            8.504121817961696e-29
        ],
        "points": 0,
        "rotation": -330.0,
        "sides": 3,
        "sizeModifier": 2.0,
        "solid": true,
        "text": "lorium ipsum",
        "trigger": {
            "destroyO2": false,
            "event": "none",
            "id": "default",
            "typeReq": 1
        },
        "txtLbl": "default",
        "velRot": 0.0,
        "velX": 0.0,
        "velY": 0.0,
        "width": 0.0
    },
    {
        "X": 25.770671844482422,
        "Y": 20.25023078918457,
        "airRes": true,
        "coefficentOfFriction": 0.5,
        "color": 707670783,
        "gravity": false,
        "height": 10.0,
        "layer": 0,
        "loc": "blank.png",
        "mass": -1.0,
        "objectType": 2,
        "pointList": [
            -0.0,
            1.0,
            0.0,
            0.0,
            0.0,
            0.0,
            1.0,
            0.0,
            301.0,
            447.0,
            0.0,
            1.0,
            1.0,
            0.0,
            0.0,
            0.0,
            0.0,
            1.0,
            0.0,
            0.0,
            0.0,
            0.0,
            1.0,
            0.0,
            0.0,
            0.0,
            0.0,
            1.0,
            3.587324068671532e-43,
            3.500496767450123e-12
        ],
        "points": 0,
        "rotation": -200.0,
        "sides": 3,
        "sizeModifier": 2.0,
        "solid": true,
        "text": "lorium ipsum",
        "trigger": {
            "destroyO2": false,
            "event": "none",
            "id": "default",
            "typeReq": 1
        },
        "txtLbl": "default",
        "velRot": 0.0,
        "velX": 0.0,
        "velY": 0.0,
        "width": 20.0
    },
    {
        "X": 51.39829635620117,
        "Y": -1.6489830017089844,
        "airRes": true,
        "coefficentOfFriction": 0.5,
        "color": 707670783,
        "gravity": false,
        "height": 10.0,
        "layer": 0,
        "loc": "blank.png",
        "mass": -1.0,
        "objectType": 2,
        "pointList": [
            -0.0,
            1.0,
            0.0,
            0.0,
            0.0,
            0.0,
            1.0,
            0.0,
            942.0,
            252.0,
            0.0,
            1.0,
            1.0,
            0.0,
            0.0,
            0.0,
            0.0,
            1.0,
            0.0,
            0.0,
            0.0,
            0.0,
            1.0,
            0.0,
            0.0,
            0.0,
            0.0,
            1.0,
            3.587324068671532e-43,
            3.500586973070874e-12
        ],
        "points": 0,
        "rotation": -240.0,
        "sides": 3,
        "sizeModifier": 2.0,
        "solid": true,
        "text": "lorium ipsum",
        "trigger": {
            "destroyO2": false,
            "event": "none",
            "id": "default",
            "typeReq": 1
        },
        "txtLbl": "default",
        "velRot": 0.0,
        "velX": 0.0,
        "velY": 0.0,
        "width": 20.0
    },
    {
        "X": 75.74755096435547,
        "Y": -26.353355407714844,
        "airRes": true,
        "coefficentOfFriction": 0.5,
        "color": 707670783,
        "gravity": false,
        "height": 10.0,
        "layer": 0,
        "loc": "blank.png",
        "mass": -1.0,
        "objectType": 2,
        "pointList": [
            -0.0,
            1.0,
            0.0,
            0.0,
            0.0,
            0.0,
            1.0,
            0.0,
            643.0,
            237.0,
            0.0,
            1.0,
            1.0,
            0.0,
            0.0,
            0.0,
            0.0,
            1.0,
            0.0,
            0.0,
            0.0,
            0.0,
            1.0,
            0.0,
            0.0,
            0.0,
            0.0,
            1.0,
            3.587324068671532e-43,
            3.5006771786916246e-12
        ],
        "points": 0,
        "rotation": -200.0,
        "sides": 3,
        "sizeModifier": 2.0,
        "solid": true,
        "text": "lorium ipsum",
        "trigger": {
            "destroyO2": false,
            "event": "none",
            "id": "default",
            "typeReq": 1
        },
        "txtLbl": "default",
        "velRot": 0.0,
        "velX": 0.0,
        "velY": 0.0,
        "width": 20.0
    },
    {
        "X": 93.33937072753906,
        "Y": -29.269245147705078,
        "airRes": true,
        "coefficentOfFriction": 0.5,
        "color": 707670783,
        "gravity": false,
        "height": 10.0,
        "layer": 0,
        "loc": "blank.png",
        "mass": -1.0,
        "objectType": 2,
        "pointList": [
            -0.0,
            1.0,
            0.0,
            0.0,
            0.0,
            0.0,
            1.0,
            0.0,
            838.0,
            121.0,
            0.0,
            1.0,
            1.0,
            0.0,
            0.0,
            0.0,
            0.0,
            1.0,
            0.0,
            0.0,
            0.0,
            0.0,
            1.0,
            0.0,
            0.0,
            0.0,
            0.0,
            1.0,
            3.587324068671532e-43,
            3.5007673843123754e-12
        ],
        "points": 0,
        "rotation": -180.0,
        "sides": 3,
        "sizeModifier": 2.0,
        "solid": true,
        "text": "lorium ipsum",
        "trigger": {
            "destroyO2": false,
            "event": "none",
            "id": "default",
            "typeReq": 1
        },
        "txtLbl": "default",
        "velRot": 0.0,
        "velX": 0.0,
        "velY": 0.0,
        "width": 20.0
    },
    {
        "X": 40.42275619506836,
        "Y": 11.73287582397461,
        "airRes": true,
        "coefficentOfFriction": 0.5,
        "color": 707670783,
        "gravity": false,
        "height": 10.0,
        "layer": 0,
        "loc": "blank.png",
        "mass": -1.0,
        "objectType": 2,
        "pointList": [
            -0.0,
            1.0,
            0.0,
            0.0,
            0.0,
            0.0,
            1.0,
            0.0,
            779.0,
            207.0,
            0.0,
            1.0,
            1.0,
            0.0,
            0.0,
            0.0,
            0.0,
            1.0,
            0.0,
            0.0,
            0.0,
            0.0,
            1.0,
            0.0,
            0.0,
            0.0,
            0.0,
            1.0,
            3.587324068671532e-43,
            3.5008575899331262e-12
        ],
        "points": 0,
        "rotation": -221.0,
        "sides": 3,
        "sizeModifier": 2.0,
        "solid": true,
        "text": "lorium ipsum",
        "trigger": {
            "destroyO2": false,
            "event": "none",
            "id": "default",
            "typeReq": 1
        },
        "txtLbl": "default",
        "velRot": 0.0,
        "velX": 0.0,
        "velY": 0.0,
        "width": 20.0
    },
    {
        "X": 62.0296745300293,
        "Y": -16.654895782470703,
        "airRes": true,
        "coefficentOfFriction": 0.5,
        "color": 707670783,
        "gravity": false,
        "height": 10.0,
        "layer": 0,
        "loc": "blank.png",
        "mass": -1.0,
        "objectType": 2,
        "pointList": [
            0.6427873969078064,
            0.7660446166992188,
            0.0,
            0.0,
            0.0,
            0.0,
            1.0,
            0.0,
            736.2561645507813,
            471.97650146484375,
            0.0,
            1.0,
            1.0,
            0.0,
            0.0,
            0.0,
            0.0,
            1.0,
            0.0,
            0.0,
            0.0,
            0.0,
            1.0,
            0.0,
            0.0,
            0.0,
            0.0,
            1.0,
            3.587324068671532e-43,
            3.500947795553877e-12
        ],
        "points": 0,
        "rotation": -230.0,
        "sides": 3,
        "sizeModifier": 2.0,
        "solid": true,
        "text": "lorium ipsum",
        "trigger": {
            "destroyO2": false,
            "event": "none",
            "id": "default",
            "typeReq": 1
        },
        "txtLbl": "default",
        "velRot": 0.0,
        "velX": 0.0,
        "velY": 0.0,
        "width": 20.0
    },
    {
        "X": 111.98143005371094,
        "Y": -27.719640731811523,
        "airRes": true,
        "coefficentOfFriction": 0.5,
        "color": 707670783,
        "gravity": false,
        "height": 10.0,
        "layer": 0,
        "loc": "blank.png",
        "mass": -1.0,
        "objectType": 2,
        "pointList": [
            0.7660441994667053,
            0.6427878737449646,
            0.0,
            0.0,
            0.0,
            0.0,
            1.0,
            0.0,
            753.46142578125,
            315.03863525390625,
            0.0,
            1.0,
            1.0,
            0.0,
            0.0,
            0.0,
            0.0,
            1.0,
            0.0,
            0.0,
            0.0,
            0.0,
            1.0,
            0.0,
            0.0,
            0.0,
            0.0,
            1.0,
            3.587324068671532e-43,
            3.501038001174628e-12
        ],
        "points": 0,
        "rotation": -170.0,
        "sides": 3,
        "sizeModifier": 2.0,
        "solid": true,
        "text": "lorium ipsum",
        "trigger": {
            "destroyO2": false,
            "event": "none",
            "id": "default",
            "typeReq": 1
        },
        "txtLbl": "default",
        "velRot": 0.0,
        "velX": 0.0,
        "velY": 0.0,
        "width": 20.0
    },
    {
        "X": 209.91567993164063,
        "Y": 208.8998260498047,
        "airRes": true,
        "coefficentOfFriction": 0.5,
        "color": 707670783,
        "gravity": false,
        "height": 10.0,
        "layer": 0,
        "loc": "blank.png",
        "mass": -1.0,
        "objectType": 0,
        "pointList": [
            -0.0,
            1.0,
            0.0,
            0.0,
            0.0,
            0.0,
            1.0,
            0.0,
            416.0,
            248.0,
            0.0,
            1.0,
            1.0,
            0.0,
            0.0,
            0.0,
            0.0,
            1.0,
            0.0,
            0.0,
            0.0,
            0.0,
            1.0,
            0.0,
            0.0,
            0.0,
            0.0,
            1.0,
            3.587324068671532e-43,
            -1.886159202660483e-16
        ],
        "points": 0,
        "rotation": 0.0,
        "sides": 3,
        "sizeModifier": 166.11619567871094,
        "solid": true,
        "text": "lorium ipsum",
        "trigger": {
            "destroyO2": false,
            "event": "none",
            "id": "default",
            "typeReq": 1
        },
        "txtLbl": "default",
        "velRot": 0.0,
        "velX": 0.0,
        "velY": 0.0,
        "width": 20.0
    },
    {
        "X": -15.116679191589355,
        "Y": -12.594087600708008,
        "airRes": true,
        "coefficentOfFriction": 0.5,
        "color": 4294967295,
        "gravity": true,
        "height": 0.0,
        "layer": 0,
        "loc": "blank.png",
        "mass": 10.0,
        "objectType": 0,
        "pointList": [
            0.4999997615814209,
            0.8660255670547485,
            0.0,
            0.0,
            0.0,
            0.0,
            1.0,
            0.0,
            396.3589782714844,
            335.3589782714844,
            0.0,
            1.0,
            1.0,
            0.0,
            0.0,
            0.0,
            0.0,
            1.0,
            0.0,
            0.0,
            0.0,
            0.0,
            1.0,
            0.0,
            0.0,
            0.0,
            0.0,
            1.0,
            3.587324068671532e-43,
            -1.8862153185932387e-16
        ],
        "points": 0,
        "rotation": -30.0,
        "sides": 3,
        "sizeModifier": 2.0,
        "solid": true,
        "text": "lorium ipsum",
        "trigger": {
            "destroyO2": false,
            "event": "none",
            "id": "default",
            "typeReq": 1
        },
        "txtLbl": "default",
        "velRot": 0.0,
        "velX": 0.0,
        "velY": 0.0,
        "width": 0.0
    },
    {
        "X": -19.108509063720703,
        "Y": -12.53590202331543,
        "airRes": true,
        "coefficentOfFriction": 0.5,
        "color": 4294967295,
        "gravity": true,
        "height": 0.0,
        "layer": 0,
        "loc": "blank.png",
        "mass": 10.0,
        "objectType": 0,
        "pointList": [
            0.4999997615814209,
            0.8660255670547485,
            0.0,
            0.0,
            0.0,
            0.0,
            1.0,
            0.0,
            396.3589782714844,
            266.3589782714844,
            0.0,
            1.0,
            1.0,
            0.0,
            0.0,
            0.0,
            0.0,
            1.0,
            0.0,
            0.0,
            0.0,
            0.0,
            1.0,
            0.0,
            0.0,
            0.0,
            0.0,
            1.0,
            3.587324068671532e-43,
            -1.8862714345259943e-16
        ],
        "points": 0,
        "rotation": 30.0,
        "sides": 3,
        "sizeModifier": 2.0,
        "solid": true,
        "text": "lorium ipsum",
        "trigger": {
            "destroyO2": false,
            "event": "none",
            "id": "default",
            "typeReq": 1
        },
        "txtLbl": "default",
        "velRot": 0.0,
        "velX": 0.0,
        "velY": 0.0,
        "width": 0.0
    },
    {
        "X": -11.301051139831543,
        "Y": 16.020450592041016,
        "airRes": true,
        "coefficentOfFriction": 0.5,
        "color": 2303797759,
        "gravity": true,
        "height": 9.16677474975586,
        "layer": -1,
        "loc": "blank.png",
        "mass": 10.0,
        "objectType": 2,
        "pointList": [
            0.0,
            0.0,
            0.0,
            0.0,
            0.0,
            0.0,
            0.0,
            0.0,
            0.0,
            0.0,
            0.0,
            0.0,
            0.0,
            0.0,
            0.0,
            0.0,
            0.0,
            0.0,
            0.0,
            0.0,
            0.0,
            0.0,
            0.0,
            0.0,
            0.0,
            0.0,
            0.0,
            0.0,
            0.0,
            0.0
        ],
        "points": 0,
        "rotation": -10.0,
        "sides": 3,
        "sizeModifier": 2.0,
        "solid": true,
        "text": "lorium ipsum",
        "trigger": {
            "destroyO2": false,
            "event": "none",
            "id": "default",
            "typeReq": 1
        },
        "txtLbl": "default",
        "velRot": 0.0,
        "velX": 0.0,
        "velY": 0.0,
        "width": 1.233917236328125
    },
    {
        "X": -12.217378616333008,
        "Y": 9.094810485839844,
        "airRes": true,
        "coefficentOfFriction": 0.5,
        "color": 2303797759,
        "gravity": true,
        "height": 8.8770751953125,
        "layer": -1,
        "loc": "blank.png",
        "mass": 10.0,
        "objectType": 2,
        "pointList": [
            0.0,
            0.0,
            0.0,
            0.0,
            0.0,
            0.0,
            0.0,
            0.0,
            0.0,
            0.0,
            0.0,
            0.0,
            0.0,
            0.0,
            0.0,
            0.0,
            0.0,
            0.0,
            0.0,
            0.0,
            0.0,
            0.0,
            0.0,
            0.0,
            0.0,
            0.0,
            0.0,
            0.0,
            0.0,
            0.0
        ],
        "points": 0,
        "rotation": -10.0,
        "sides": 3,
        "sizeModifier": 2.0,
        "solid": true,
        "text": "lorium ipsum",
        "trigger": {
            "destroyO2": false,
            "event": "none",
            "id": "default",
            "typeReq": 1
        },
        "txtLbl": "default",
        "velRot": 0.0,
        "velX": 0.0,
        "velY": 0.0,
        "width": 12.795891761779785
    },
    {
        "X": -12.81805419921875,
        "Y": 8.319073677062988,
        "airRes": true,
        "coefficentOfFriction": 0.5,
        "color": 4294967295,
        "gravity": true,
        "height": 3.749553680419922,
        "layer": 0,
        "loc": "blank.png",
        "mass": 10.0,
        "objectType": 4,
        "pointList": [
            4.5912142885138307e-41,
            -1.2170058845254706e-22,
            4.5912142885138307e-41,
            -1.2170075253561534e-22,
            4.5912142885138307e-41,
            7.296511214237994e-17,
            4.431606393427234e-41,
            3.363116314379561e-44,
            543.394287109375,
            -1.217005632089981e-22,
            4.5912142885138307e-41,
            0.0,
            0.0,
            2.6366919758658014e-09,
            2.7179983958798043e+23,
            0.0,
            0.0,
            7.264202201256163e-17,
            4.431606393427234e-41,
            8.407790785948902e-45,
            0.0,
            0.0,
            0.0,
            5.7425211068031e-42,
            0.0,
            2.802596928649634e-45,
            0.0,
            0.0,
            0.0,
            0.0
        ],
        "points": 0,
        "rotation": -10.0,
        "sides": 3,
        "sizeModifier": 24.0,
        "solid": true,
        "text": "hi :)",
        "trigger": {
            "destroyO2": false,
            "event": "none",
            "id": "default",
            "typeReq": 1
        },
        "txtLbl": "default",
        "velRot": 0.0,
        "velX": 0.0,
        "velY": 0.0,
        "width": 11.068304061889648
    },
    {
        "X": -15.133232116699219,
        "Y": -5.7121968269348145,
        "airRes": true,
        "coefficentOfFriction": 0.5,
        "color": 4294967295,
        "gravity": true,
        "height": 0.0,
        "layer": 0,
        "loc": "blank.png",
        "mass": 10.0,
        "objectType": 0,
        "pointList": [
            -0.0,
            1.0,
            0.0,
            0.0,
            0.0,
            0.0,
            1.0,
            0.0,
            231.71249389648438,
            284.1369934082031,
            0.0,
            1.0,
            1.0,
            0.0,
            0.0,
            0.0,
            0.0,
            1.0,
            0.0,
            0.0,
            0.0,
            0.0,
            1.0,
            0.0,
            0.0,
            0.0,
            0.0,
            1.0,
            3.587324068671532e-43,
            8.504121817961696e-29
        ],
        "points": 0,
        "rotation": -390.0,
        "sides": 3,
        "sizeModifier": 1.9145588874816895,
        "solid": true,
        "text": "lorium ipsum",
        "trigger": {
            "destroyO2": false,
            "event": "none",
            "id": "default",
            "typeReq": 1
        },
        "txtLbl": "default",
        "velRot": 0.0,
        "velX": 0.0,
        "velY": 0.0,
        "width": 0.0
    },
    {
        "X": 0.5432369709014893,
        "Y": -11.284785270690918,
        "airRes": true,
        "coefficentOfFriction": 0.5,
        "color": 16711935,
        "gravity": true,
        "height": 0.0,
        "layer": 0,
        "loc": "blank.png",
        "mass": 10.0,
        "objectType": 3,
        "pointList": [
            3.9283814430236816,
            2.442392587661743,
            2.0283825397491455,
            -1.3576024770736694,
            0.39020836353302,
            -3.46339750289917,
            -1.2097892761230469,
            -2.4133968353271484,
            -1.7597968578338623,
            -1.163385033607483,
            -3.1717629432678223,
            2.2923920154571533,
            -0.20562340319156647,
            3.662997007369995,
            0.0,
            0.0,
            0.0,
            0.0,
            0.0,
            0.0,
            0.0,
            0.0,
            0.0,
            0.0,
            0.0,
            0.0,
            0.0,
            0.0,
            0.0,
            0.0
        ],
        "points": 7,
        "rotation": 0.0,
        "sides": 3,
        "sizeModifier": 2.0,
        "solid": true,
        "text": "lorium ipsum",
        "trigger": {
            "destroyO2": false,
            "event": "none",
            "id": "default",
            "typeReq": 1
        },
        "txtLbl": "default",
        "velRot": 0.0,
        "velX": 0.0,
        "velY": 0.0,
        "width": 0.0
    }
]